discord_raw_mcp/__init__.py
discord_raw_mcp/__main__.py
discord_raw_mcp/server.py
iflow_mcp_discord_raw_mcp-0.1.0.dist-info/METADATA
iflow_mcp_discord_raw_mcp-0.1.0.dist-info/WHEEL
iflow_mcp_discord_raw_mcp-0.1.0.dist-info/entry_points.txt
iflow_mcp_discord_raw_mcp-0.1.0.dist-info/licenses/LICENSE
iflow_mcp_discord_raw_mcp-0.1.0.dist-info/RECORD
