Metadata-Version: 2.4
Name: iflow-mcp_discord-raw-mcp
Version: 0.1.0
Summary: Discord Raw API MCP Server
Author-email: Your Name <your.email@example.com>
License-File: LICENSE
Requires-Python: >=3.10
Requires-Dist: aiohttp>=3.9.1
Requires-Dist: discord-py>=2.3.2
Requires-Dist: mcp>=1.2.0
